setup_server.py
pse_messanger_server.egg-info/PKG-INFO
pse_messanger_server.egg-info/SOURCES.txt
pse_messanger_server.egg-info/dependency_links.txt
pse_messanger_server.egg-info/requires.txt
pse_messanger_server.egg-info/top_level.txt
server/__init__.py
server/server.py
server/common/__init__.py
server/common/decos.py
server/common/descriptors.py
server/common/errors.py
server/common/metaclasses.py
server/common/utils.py
server/common/variables.py
server/db/__init__.py
server/db/db_server.py
server/server/__init__.py
server/server/gui_server.py